MANIFEST.in
README.md
setup.py
audiotool/__init__.py
audiotool/get_audio_timestamp.py
audiotool/main_speaker_extract.py
audiotool/pipeline_annote.py
audiotool/pipeline_ms.py
audiotool/utils.py
audiotool/version.py
audiotool.egg-info/PKG-INFO
audiotool.egg-info/SOURCES.txt
audiotool.egg-info/dependency_links.txt
audiotool.egg-info/entry_points.txt
audiotool.egg-info/requires.txt
audiotool.egg-info/top_level.txt
audiotool/audioeffect/__init__.py
audiotool/audioeffect/speed_one.py
audiotool/audioenhance/__init__.py
audiotool/audioenhance/enhance_one.py
audiotool/audioenhance/clearvoice/__init__.py
audiotool/audioenhance/clearvoice/clearvoice.py
audiotool/audioenhance/clearvoice/network_wrapper.py
audiotool/audioenhance/clearvoice/networks.py
audiotool/audioenhance/clearvoice/config/inference/AV_MossFormer2_TSE_16K.yaml
audiotool/audioenhance/clearvoice/config/inference/FRCRN_SE_16K.yaml
audiotool/audioenhance/clearvoice/config/inference/MossFormer2_SE_48K.yaml
audiotool/audioenhance/clearvoice/config/inference/MossFormer2_SS_16K.yaml
audiotool/audioenhance/clearvoice/config/inference/MossFormerGAN_SE_16K.yaml
audiotool/audioenhance/clearvoice/dataloader/__init__.py
audiotool/audioenhance/clearvoice/dataloader/dataloader.py
audiotool/audioenhance/clearvoice/dataloader/misc.py
audiotool/audioenhance/clearvoice/models/__init__.py
audiotool/audioenhance/clearvoice/models/av_mossformer2_tse/__init__.py
audiotool/audioenhance/clearvoice/models/av_mossformer2_tse/av_mossformer2.py
audiotool/audioenhance/clearvoice/models/av_mossformer2_tse/visual_frontend.py
audiotool/audioenhance/clearvoice/models/av_mossformer2_tse/faceDetector/__init__.py
audiotool/audioenhance/clearvoice/models/av_mossformer2_tse/faceDetector/s3fd/__init__.py
audiotool/audioenhance/clearvoice/models/av_mossformer2_tse/faceDetector/s3fd/box_utils.py
audiotool/audioenhance/clearvoice/models/av_mossformer2_tse/faceDetector/s3fd/nets.py
audiotool/audioenhance/clearvoice/models/av_mossformer2_tse/mossformer/__init__.py
audiotool/audioenhance/clearvoice/models/av_mossformer2_tse/mossformer/utils/Transformer.py
audiotool/audioenhance/clearvoice/models/av_mossformer2_tse/mossformer/utils/__init__.py
